stravapy/__init__.py
stravapy/datapoint.py
stravapy/file_reader.py
stravapy-0.0.1.dist-info/LICENSE.txt
stravapy-0.0.1.dist-info/METADATA
stravapy-0.0.1.dist-info/WHEEL
stravapy-0.0.1.dist-info/top_level.txt
stravapy-0.0.1.dist-info/RECORD
